ganglia/__init__.py
ganglia/ganglia.py
ganglia/ganglia_test.py
ganglia/test_ganglia.py
ganglia-0.3.0.dist-info/METADATA
ganglia-0.3.0.dist-info/metadata.json
ganglia-0.3.0.dist-info/RECORD
ganglia-0.3.0.dist-info/top_level.txt
ganglia-0.3.0.dist-info/WHEEL
