Metadata-Version: 2.0
Name: ganglia
Version: 0.3.0
Summary: A Ganglia client
Home-page: UNKNOWN
Author: Timothée Peignier
Author-email: timothee.peignier@tryphon.org
License: MIT
Platform: UNKNOWN
Classifier: Intended Audience :: Developers
Classifier: Development Status :: 5 - Production/Stable
Classifier: License :: OSI Approved :: MIT License
Classifier: Operating System :: OS Independent
Classifier: Programming Language :: Python
Classifier: Programming Language :: Python :: 3
Classifier: Topic :: Utilities
